{"ActiveFlag":"y","ChildItemId":0,"DeviceName":"Healing Potion","IconId":2929,"ItemDescription":{"Description":"This consumable heals you over time.","Menuitems":[],"SecondaryDescription":"This consumable heals 250 Health over 25 seconds."},"ItemId":7621,"ItemTier":1,"Price":50,"RestrictedRoles":"no restrictions","RootItemId":7621,"ShortDesc":"Restores Health over time.","StartingItem":false,"Type":"Consumable","itemIcon_URL":"https://web2.hirez.com/smite/item-icons/healing-potion.jpg","ret_msg":null}
