{"ActiveFlag":"y","ChildItemId":0,"DeviceName":"Hidden Dagger","IconId":2856,"ItemDescription":{"Description":"Physical Power and Critical Chance.","Menuitems":[{"Description":"Physical Power","Value":"+10"},{"Description":"Critical Strike Chance","Value":"+5%"}],"SecondaryDescription":null},"ItemId":9812,"ItemTier":1,"Price":700,"RestrictedRoles":"no restrictions","RootItemId":9812,"ShortDesc":"Physical Power and Critical Chance.","StartingItem":false,"Type":"Item","itemIcon_URL":"https://web2.hirez.com/smite/item-icons/hidden-dagger.jpg","ret_msg":null}
