{"ActiveFlag":"y","ChildItemId":0,"DeviceName":"Vision Shard","IconId":8136,"ItemDescription":{"Description":null,"Menuitems":[],"SecondaryDescription":"Using this item places a ward that lasts 60 seconds. Vision Shard can be upgraded to a new relic once you reach Level 12. Cooldown - 120s."},"ItemId":18307,"ItemTier":1,"Price":0,"RestrictedRoles":"no restrictions","RootItemId":18307,"ShortDesc":"Allows you to place a short duration ward","StartingItem":false,"Type":"Active","itemIcon_URL":"https://web2.hirez.com/smite/item-icons/vision-shard.jpg","ret_msg":null}
