{"ActiveFlag":"y","ChildItemId":10190,"DeviceName":"Warded Shield","IconId":2906,"ItemDescription":{"Description":"","Menuitems":[{"Description":"Physical Power","Value":"+15"},{"Description":"Magical Protection","Value":"+35"}],"SecondaryDescription":""},"ItemId":9835,"ItemTier":2,"Price":750,"RestrictedRoles":"no restrictions","RootItemId":10190,"ShortDesc":"Physical Power and Magical Protection.","StartingItem":false,"Type":"Item","itemIcon_URL":"https://web2.hirez.com/smite/item-icons/warded-shield.jpg","ret_msg":null}
