[{"godIcon_URL":"https://web2.hirez.com/smite/god-icons/vamana.jpg","godSkin_URL":"https://web2.hirez.com/smite/god-skins/vamana_cangaceiro.jpg","god_id":1723,"god_name":"Vamana","obtainability":"Exclusivo de baú","price_favor":0,"price_gems":0,"ret_msg":null,"skin_id1":13023,"skin_id2":11411,"skin_name":"Cangaceiro"},{"godIcon_URL":"https://web2.hirez.com/smite/god-icons/vamana.jpg","godSkin_URL":"","god_id":1723,"god_name":"Vamana","obtainability":"Normal","price_favor":15000,"price_gems":400,"ret_msg":null,"skin_id1":10874,"skin_id2":10419,"skin_name":"Diamante"},{"godIcon_URL":"https://web2.hirez.com/smite/god-icons/vamana.jpg","godSkin_URL":"https://web2.hirez.com/smite/god-skins/vamana_golden.jpg","god_id":1723,"god_name":"Vamana","obtainability":"Normal","price_favor":9500,"price_gems":200,"ret_msg":null,"skin_id1":8848,"skin_id2":8306,"skin_name":"Dourada"},{"godIcon_URL":"https://web2.hirez.com/smite/god-icons/vamana.jpg","godSkin_URL":"","god_id":1723,"god_name":"Vamana","obtainability":"Normal","price_favor":12500,"price_gems":300,"ret_msg":null,"skin_id1":9461,"skin_id2":9321,"skin_name":"Lendária"},{"godIcon_URL":"https://web2.hirez.com/smite/god-icons/vamana.jpg","godSkin_URL":"https://web2.hirez.com/smite/god-skins/vamana_lil-mana.jpg","god_id":1723,"god_name":"Vamana","obtainability":"Normal","price_favor":0,"price_gems":600,"ret_msg":null,"skin_id1":8941,"skin_id2":8770,"skin_name":"MC Va'Mano"},{"godIcon_URL":"https://web2.hirez.com/smite/god-icons/vamana.jpg","godSkin_URL":"https://web2.hirez.com/smite/god-skins/vamana_divine-protector.jpg","god_id":1723,"god_name":"Vamana","obtainability":"Normal","price_favor":9500,"price_gems":100,"ret_msg":null,"skin_id1":8514,"skin_id2":7781,"skin_name":"Protetor Divino"},{"godIcon_URL":"https://web2.hirez.com/smite/god-icons/vamana.jpg","godSkin_URL":"https://web2.hirez.com/smite/god-skins/vamana_rakshasa.jpg","god_id":1723,"god_name":"Vamana","obtainability":"Normal","price_favor":0,"price_gems":250,"ret_msg":null,"skin_id1":19363,"skin_id2":12861,"skin_name":"Rakshasa"},{"godIcon_URL":"https://web2.hirez.com/smite/god-icons/vamana.jpg","godSkin_URL":"https://web2.hirez.com/smite/god-skins/vamana_serenity.jpg","god_id":1723,"god_name":"Vamana","obtainability":"Exclusivo de baú","price_favor":0,"price_gems":0,"ret_msg":null,"skin_id1":31898,"skin_id2":14926,"skin_name":"Serenidade"},{"godIcon_URL":"https://web2.hirez.com/smite/god-icons/vamana.jpg","godSkin_URL":"https://web2.hirez.com/smite/god-skins/vamana_touchdown.jpg","god_id":1723,"god_name":"Vamana","obtainability":"Exclusivo de baú","price_favor":0,"price_gems":0,"ret_msg":null,"skin_id1":52237,"skin_id2":17228,"skin_name":"Touchdown"},{"godIcon_URL":"https://web2.hirez.com/smite/god-icons/vamana.jpg","godSkin_URL":"https://web2.hirez.com/smite/god-skins/vamana_standard-vamana.jpg","god_id":1723,"god_name":"Vamana","obtainability":"Normal","price_favor":0,"price_gems":0,"ret_msg":null,"skin_id1":8423,"skin_id2":7886,"skin_name":"Vamana Padrão"}]
